Metadata-Version: 1.0
Name: alwaysdata-dyn-dns
Version: 1.0.0
Summary: Lightweight HTTP server to update Alwaysdata DNS entries, typically from a dynamic DNS client such as a home router.
Home-page: https://github.com/zopieux/alwaysdata-dyn-dns/
Author: Alexandre Macabies
Author-email: UNKNOWN
License: MIT
Platform: UNKNOWN
